pvactools/lib/__init__.py
pvactools/lib/aggregate_all_epitopes.py
pvactools/lib/allele_specific_binding_filter.py
pvactools/lib/allele_specific_cutoffs.py
pvactools/lib/anchor_residue_pass.py
pvactools/lib/binding_filter.py
pvactools/lib/calculate_manufacturability.py
pvactools/lib/calculate_reference_proteome_similarity.py
pvactools/lib/call_iedb.py
pvactools/lib/call_mhcnuggets.py
pvactools/lib/color_peptides51mer.py
pvactools/lib/combine_inputs.py
pvactools/lib/combine_parsed_outputs.py
pvactools/lib/csq_parser.py
pvactools/lib/download_example_data.py
pvactools/lib/fasta_generator.py
pvactools/lib/fasta_to_kmers.py
pvactools/lib/filter.py
pvactools/lib/filter_regtools_results.py
pvactools/lib/generate_reviews_files.py
pvactools/lib/get_best_candidate.py
pvactools/lib/identify_problematic_amino_acids.py
pvactools/lib/input_file_converter.py
pvactools/lib/junction_to_fasta.py
pvactools/lib/load_gtf_data.py
pvactools/lib/mark_genes_of_interest.py
pvactools/lib/net_chop.py
pvactools/lib/netmhc_stab.py
pvactools/lib/optimal_peptide.py
pvactools/lib/output_parser.py
pvactools/lib/pipeline.py
pvactools/lib/post_processor.py
pvactools/lib/prediction_class.py
pvactools/lib/prediction_class_utils.py
pvactools/lib/print_log.py
pvactools/lib/proximal_variant.py
pvactools/lib/pvacvector_input_fasta_generator.py
pvactools/lib/run_argument_parser.py
pvactools/lib/run_utils.py
pvactools/lib/sort.py
pvactools/lib/splice_pipeline.py
pvactools/lib/top_score_filter.py
pvactools/lib/transcript_filter.py
pvactools/lib/update_tiers.py
pvactools/lib/valid_algorithms.py
pvactools/lib/valid_alleles.py
pvactools/lib/valid_netmhciipan_versions.py
pvactools/lib/vector_visualization.py
pvactools/supporting_files/cancer_census_hotspot_gene_list.tsv
pvactools/tools/__init__.py
pvactools/tools/compare.py
pvactools/tools/download_cwls.py
pvactools/tools/download_wdls.py
pvactools/tools/main.py
pvactools/tools/pvacbind/__init__.py
pvactools/tools/pvacbind/allele_specific_cutoffs.py
pvactools-6.0.5.dist-info/licenses/LICENSE
pvactools-6.0.5.dist-info/METADATA
pvactools-6.0.5.dist-info/WHEEL
pvactools-6.0.5.dist-info/entry_points.txt
pvactools-6.0.5.dist-info/top_level.txt
pvactools-6.0.5.dist-info/RECORD
