Metadata-Version: 2.4
Name: pvactools
Version: 6.0.5
Summary: A cancer immunotherapy tools suite
Home-page: https://github.com/griffithlab/pVACtools
Author: Jasreet Hundal, Susanna Kiwala, Joshua McMichael, Christopher A Miller, Alexander T Wollam, Huiming Xia, Connor J Liu, Sidi Zhao, Yang-Yang Feng, Aaron P Graubert, Amber Z Wollam, Jonas Neichin, Megan Neveau, Jason Walker, William E Gillanders, Elaine R Mardis, Obi L Griffith, Malachi Griffith
Author-email: help@pvactools.org
License: BSD-3-Clause-Clear
Keywords: antigens neoantigens cancer sequencing variant variants fusion fusions
Classifier: Development Status :: 4 - Beta
Classifier: Intended Audience :: Science/Research
Classifier: Topic :: Scientific/Engineering :: Bio-Informatics
Classifier: Programming Language :: Python :: 3.9
Classifier: Programming Language :: Python :: 3.10
Classifier: Programming Language :: Python :: 3.11
License-File: LICENSE
Requires-Dist: vcfpy==0.13.8
Requires-Dist: requests
Requires-Dist: PyYAML>=5.1
Requires-Dist: biopython==1.77
Requires-Dist: networkx
Requires-Dist: simanneal
Requires-Dist: pandas<2.1.0
Requires-Dist: wget
Requires-Dist: pysam
Requires-Dist: Pillow
Requires-Dist: pymp-pypi
Requires-Dist: mock
Requires-Dist: vaxrank>=1.1.0
Requires-Dist: varcode>=1.1.0
Requires-Dist: mhcnuggets==2.4.1
Requires-Dist: mhcflurry==2.0.6
Requires-Dist: testfixtures
Requires-Dist: gtfparse==2.0.1
Requires-Dist: pyfaidx>=0.7.1
Requires-Dist: fsspec<=2025.3.0
Requires-Dist: packaging
Requires-Dist: pyarrow
Requires-Dist: polars==0.16.18
Requires-Dist: XlsxWriter
Requires-Dist: openpyxl
Requires-Dist: deepdiff
Dynamic: author
Dynamic: author-email
Dynamic: classifier
Dynamic: description
Dynamic: home-page
Dynamic: keywords
Dynamic: license
Dynamic: license-file
Dynamic: requires-dist
Dynamic: summary
